rtl/planeController.v
module planeController 
#(
    parameter   OUT_NUM = 64,
    parameter   D_WIDTH = 8,    // Memory interface data bus width
    parameter   C_WIDTH = 5    // PWM counter width
)
(
    input       clk,
    input       reset,
    input       [D_WIDTH - 1:0] dataIn,
    input       dataEn,
    input       rs,
    output reg  [OUT_NUM - 1:0] pwmOut
);

reg [C_WIDTH - 1:0] mem [0:OUT_NUM - 1];
reg [D_WIDTH - 2:0] memAddr; // Address that will be rewrited
reg incDec; // Decrement address by default
reg pwmEnabled; // Enable pwm output
reg [C_WIDTH - 1:0] cnt;
reg oldDataEn;

integer j;
// Memory interface
always @(posedge clk)
begin
    if (!reset) begin
        pwmEnabled <= 0;
        memAddr <= 0;
        incDec <= 0;
        for (j = 0; j < OUT_NUM; j = j + 1)
            mem[j] <= 'b0;
    end else begin
        if (dataEn == 1'b0 && oldDataEn == 1'b1) begin
            if (rs == 1'b1) begin
                casex(dataIn)
                    8'b0000_0001: begin // Clear memory
                        for (j = 0; j < OUT_NUM; j = j + 1)
                            mem[j] <= 'b0;
                    end
                    8'b0000_001?: memAddr <= 'b0; // Zero address
                    8'b0000_01??: incDec <= dataIn[1];
                    8'b0000_1???: pwmEnabled <= dataIn[2];
                    8'b1???_????: memAddr <= dataIn[D_WIDTH - 2:0]; // Set address
                    default: $display("Error: no such command");
                endcase
            end else begin
                mem[memAddr] <= dataIn;
                if (incDec)
                    memAddr <= memAddr + 'b1;
                else
                    memAddr <= memAddr - 'b1;
            end
        end
    end

    oldDataEn <= dataEn;
end

// counter
always @(posedge clk)
begin
    if (!reset) begin
        cnt <= 0;
    end else begin
        cnt <= cnt + 1;
    end
end

genvar i;
generate
for (i = 0; i < OUT_NUM; i = i + 1) begin: pwmOuts
    always @(posedge clk) begin
        //        if (pwmEnabled == 1'b1) begin
        //            if (cnt == 0) begin
        //                if (mem[i] != 0) begin
        //                    pwmOut[i] <= 1'b1;
        //                end else begin
        //                    pwmOut[i] <= 1'b0;
        //                end
        //            end else begin
        //                if (mem[i] == cnt)
        //                    pwmOut[i] <= 1'b0;
        //            end
        //        end else begin
        //            pwmOut[i] <= 1'b0;
        //        end

        if (pwmEnabled == 1'b1) begin
            if (cnt <= mem[i] ) begin
                pwmOut[i] <= 1'b1;
            end else begin
                pwmOut[i] <= 1'b0;
            end
        end
    end
end
endgenerate

endmodule // planeController

bench/simple_tb/pwmGenerator_tb.v
`include "timescale.v"

module testPWM;

localparam   OUT_NUM = 8;
localparam   D_WIDTH = 8;    // Memory interface data bus widt;
localparam   C_WIDTH = 5;    // PWM counter width

localparam SYSCLK_DELAY = 10;

reg  reset, clk, clk4;
reg  [D_WIDTH - 1:0] data;
wire [OUT_NUM - 1:0] pwmOut;
reg dataEn, rs;

integer i;

planeController  pc(
    .clk(clk), 
    .reset(reset), 
    .dataIn(data), 
    .dataEn(dataEn), 
    .rs(rs), 
    .pwmOut(pwmOut)
);

defparam
    pc.OUT_NUM = OUT_NUM;

// clk
always
    #SYSCLK_DELAY clk = ~clk;

// clk
always
    #(SYSCLK_DELAY*4) clk4 = ~clk4;

initial
begin
    clk = 0;
    clk4 = 0;
    reset = 0;
    for (i = 0; i < 5; i = i + 1)
        @(posedge clk);
    reset = 1;
    for (i = 0; i < 5; i = i + 1)
        @(posedge clk);

    send_command(8'b0000_0001, 1'b1);
    send_command(8'b0000_0010, 1'b1);
    send_command(8'b0000_0110, 1'b1);
    send_command(8'b0000_1100, 1'b1);

    send_command(8'b0000_0000, 1'b0);
    send_command(8'b0000_1111, 1'b0);
    send_command(8'b0000_1111, 1'b0);
    send_command(8'b0000_1111, 1'b0);

    send_command(8'b1111_1111, 1'b0);
    send_command(8'b1111_1111, 1'b0);
    send_command(8'b1111_1111, 1'b0);
    send_command(8'b1111_1111, 1'b0);

    #10000
    $finish;
end

// создаем файл VCD для последующего анализа сигналов
initial
begin
    $dumpfile("testPWM.vcd");
    $dumpvars(0, testPWM);
end

// наблюдаем за некоторыми сигналами системы
//initial
//$monitor($stime,, reset,, clk);

task send_command (
    input [7:0] dataIn,
    input rsIn
);
begin
    rs = rsIn;
    dataEn = 1;
    data = dataIn;
    @(posedge clk4);
    dataEn = 0;
    @(posedge clk4);
end
endtask // send_command

endmodule // testPWM

sim/testPWM.vcd
$date
	Tue Dec 18 04:15:46 2012
$end
$version
	Icarus Verilog
$end
$timescale
	1ps
$end
$scope module testPWM $end
$var wire 8 ! pwmOut [7:0] $end
$var reg 1 " clk $end
$var reg 1 # clk4 $end
$var reg 8 $ data [7:0] $end
$var reg 1 % dataEn $end
$var integer 32 & i [31:0] $end
$var reg 1 ' reset $end
$var reg 1 ( rs $end
$scope module pc $end
$var wire 1 ) clk $end
$var wire 1 * dataEn $end
$var wire 8 + dataIn [7:0] $end
$var wire 1 , reset $end
$var wire 1 - rs $end
$var reg 5 . cnt [4:0] $end
$var reg 1 / incDec $end
$var integer 32 0 j [31:0] $end
$var reg 7 1 memAddr [6:0] $end
$var reg 1 2 oldDataEn $end
$var reg 1 3 pwmEnabled $end
$var reg 8 4 pwmOut [7:0] $end
$scope begin pwmOuts[0] $end
$upscope $end
$scope begin pwmOuts[1] $end
$upscope $end
$scope begin pwmOuts[2] $end
$upscope $end
$scope begin pwmOuts[3] $end
$upscope $end
$scope begin pwmOuts[4] $end
$upscope $end
$scope begin pwmOuts[5] $end
$upscope $end
$scope begin pwmOuts[6] $end
$upscope $end
$scope begin pwmOuts[7] $end
$upscope $end
$upscope $end
$scope task send_command $end
$var reg 8 5 dataIn [7:0] $end
$var reg 1 6 rsIn $end
$upscope $end
$upscope $end
$enddefinitions $end
#0
$dumpvars
x6
bx 5
bx 4
x3
x2
bx 1
bx 0
x/
bx .
x-
0,
bx +
x*
0)
x(
0'
b0 &
x%
bx $
0#
0"
bx !
$end
#10000
0/
b0 1
03
b0 .
b1000 0
b1 &
1"
1)
#20000
0"
0)
#30000
b10 &
b1000 0
1"
1)
#40000
0"
0)
1#
#50000
b1000 0
b11 &
1"
1)
#60000
0"
0)
#70000
b100 &
b1000 0
1"
1)
#80000
0"
0)
0#
#90000
b1 .
1'
1,
b0 &
1"
1)
#100000
0"
0)
#110000
b1 &
b10 .
1"
1)
#120000
0"
0)
1#
#130000
b11 .
b10 &
1"
1)
#140000
0"
0)
#150000
b11 &
b100 .
1"
1)
#160000
0"
0)
0#
#170000
b101 .
b100 &
1"
1)
#180000
0"
0)
#190000
b1 $
b1 +
1%
1*
1(
1-
16
b1 5
b101 &
b110 .
1"
1)
#200000
0%
0*
0"
0)
1#
#210000
02
b111 .
1"
1)
#220000
0"
0)
#230000
b1000 .
1"
1)
#240000
0"
0)
0#
#250000
b1001 .
1"
1)
#260000
0"
0)
#270000
b1010 .
1"
1)
#280000
b10 $
b10 +
1%
1*
b10 5
0"
0)
1#
#290000
12
b1011 .
1"
1)
#300000
0"
0)
#310000
b1100 .
1"
1)
#320000
0"
0)
0#
#330000
b1101 .
1"
1)
#340000
0"
0)
#350000
b1110 .
1"
1)
#360000
0%
0*
0"
0)
1#
#370000
02
b1111 .
1"
1)
#380000
0"
0)
#390000
b10000 .
1"
1)
#400000
0"
0)
0#
#410000
b10001 .
1"
1)
#420000
0"
0)
#430000
b10010 .
1"
1)
#440000
b110 $
b110 +
1%
1*
b110 5
0"
0)
1#
#450000
12
b10011 .
1"
1)
#460000
0"
0)
#470000
b10100 .
1"
1)
#480000
0"
0)
0#
#490000
b10101 .
1"
1)
#500000
0"
0)
#510000
b10110 .
1"
1)
#520000
0%
0*
0"
0)
1#
#530000
02
1/
b10111 .
1"
1)
#540000
0"
0)
#550000
b11000 .
1"
1)
#560000
0"
0)
0#
#570000
b11001 .
1"
1)
#580000
0"
0)
#590000
b11010 .
1"
1)
#600000
b1100 $
b1100 +
1%
1*
b1100 5
0"
0)
1#
#610000
12
b11011 .
1"
1)
#620000
0"
0)
#630000
b11100 .
1"
1)
#640000
0"
0)
0#
#650000
b11101 .
1"
1)
#660000
0"
0)
#670000
b11110 .
1"
1)
#680000
0%
0*
0"
0)
1#
#690000
02
13
b11111 .
1"
1)
#700000
0"
0)
#710000
b0 4
b0 !
b0 .
1"
1)
#720000
0"
0)
0#
#730000
b0 4
b1 .
1"
1)
#740000
0"
0)
#750000
b0 4
b10 .
1"
1)
#760000
b0 $
b0 +
1%
1*
0(
0-
06
b0 5
0"
0)
1#
#770000
b0 4
12
b11 .
1"
1)
#780000
0"
0)
#790000
b0 4
b100 .
1"
1)
#800000
0"
0)
0#
#810000
b0 4
b101 .
1"
1)
#820000
0"
0)
#830000
b0 4
b110 .
1"
1)
#840000
0%
0*
0"
0)
1#
#850000
b0 4
02
b1 1
b111 .
1"
1)
#860000
0"
0)
#870000
b0 4
b1000 .
1"
1)
#880000
0"
0)
0#
#890000
b0 4
b1001 .
1"
1)
#900000
0"
0)
#910000
b0 4
b1010 .
1"
1)
#920000
b1111 $
b1111 +
1%
1*
b1111 5
0"
0)
1#
#930000
b0 4
12
b1011 .
1"
1)
#940000
0"
0)
#950000
b0 4
b1100 .
1"
1)
#960000
0"
0)
0#
#970000
b0 4
b1101 .
1"
1)
#980000
0"
0)
#990000
b0 4
b1110 .
1"
1)
#1000000
0%
0*
0"
0)
1#
#1010000
b0 4
02
b10 1
b1111 .
1"
1)
#1020000
0"
0)
#1030000
b10 !
b10 4
b10000 .
1"
1)
#1040000
0"
0)
0#
#1050000
b0 !
b0 4
b10001 .
1"
1)
#1060000
0"
0)
#1070000
b0 4
b10010 .
1"
1)
#1080000
1%
1*
0"
0)
1#
#1090000
b0 4
12
b10011 .
1"
1)
#1100000
0"
0)
#1110000
b0 4
b10100 .
1"
1)
#1120000
0"
0)
0#
#1130000
b0 4
b10101 .
1"
1)
#1140000
0"
0)
#1150000
b0 4
b10110 .
1"
1)
#1160000
0%
0*
0"
0)
1#
#1170000
b0 4
02
b11 1
b10111 .
1"
1)
#1180000
0"
0)
#1190000
b0 4
b11000 .
1"
1)
#1200000
0"
0)
0#
#1210000
b0 4
b11001 .
1"
1)
#1220000
0"
0)
#1230000
b0 4
b11010 .
1"
1)
#1240000
1%
1*
0"
0)
1#
#1250000
b0 4
12
b11011 .
1"
1)
#1260000
0"
0)
#1270000
b0 4
b11100 .
1"
1)
#1280000
0"
0)
0#
#1290000
b0 4
b11101 .
1"
1)
#1300000
0"
0)
#1310000
b0 4
b11110 .
1"
1)
#1320000
0%
0*
0"
0)
1#
#1330000
b0 4
02
b100 1
b11111 .
1"
1)
#1340000
0"
0)
#1350000
b0 4
b0 .
1"
1)
#1360000
0"
0)
0#
#1370000
b1110 !
b1110 4
b1 .
1"
1)
#1380000
0"
0)
#1390000
b1110 4
b10 .
1"
1)
#1400000
b11111111 $
b11111111 +
1%
1*
b11111111 5
0"
0)
1#
#1410000
b1110 4
12
b11 .
1"
1)
#1420000
0"
0)
#1430000
b1110 4
b100 .
1"
1)
#1440000
0"
0)
0#
#1450000
b1110 4
b101 .
1"
1)
#1460000
0"
0)
#1470000
b1110 4
b110 .
1"
1)
#1480000
0%
0*
0"
0)
1#
#1490000
b1110 4
02
b101 1
b111 .
1"
1)
#1500000
0"
0)
#1510000
b11110 !
b11110 4
b1000 .
1"
1)
#1520000
0"
0)
0#
#1530000
b11110 4
b1001 .
1"
1)
#1540000
0"
0)
#1550000
b11110 4
b1010 .
1"
1)
#1560000
1%
1*
0"
0)
1#
#1570000
b11110 4
12
b1011 .
1"
1)
#1580000
0"
0)
#1590000
b11110 4
b1100 .
1"
1)
#1600000
0"
0)
0#
#1610000
b11110 4
b1101 .
1"
1)
#1620000
0"
0)
#1630000
b11110 4
b1110 .
1"
1)
#1640000
0%
0*
0"
0)
1#
#1650000
b11110 4
02
b110 1
b1111 .
1"
1)
#1660000
0"
0)
#1670000
b111110 !
b111110 4
b10000 .
1"
1)
#1680000
0"
0)
0#
#1690000
b110000 !
b110000 4
b10001 .
1"
1)
#1700000
0"
0)
#1710000
b110000 4
b10010 .
1"
1)
#1720000
1%
1*
0"
0)
1#
#1730000
b110000 4
12
b10011 .
1"
1)
#1740000
0"
0)
#1750000
b110000 4
b10100 .
1"
1)
#1760000
0"
0)
0#
#1770000
b110000 4
b10101 .
1"
1)
#1780000
0"
0)
#1790000
b110000 4
b10110 .
1"
1)
#1800000
0%
0*
0"
0)
1#
#1810000
b110000 4
02
b111 1
b10111 .
1"
1)
#1820000
0"
0)
#1830000
b1110000 !
b1110000 4
b11000 .
1"
1)
#1840000
0"
0)
0#
#1850000
b1110000 4
b11001 .
1"
1)
#1860000
0"
0)
#1870000
b1110000 4
b11010 .
1"
1)
#1880000
1%
1*
0"
0)
1#
#1890000
b1110000 4
12
b11011 .
1"
1)
#1900000
0"
0)
#1910000
b1110000 4
b11100 .
1"
1)
#1920000
0"
0)
0#
#1930000
b1110000 4
b11101 .
1"
1)
#1940000
0"
0)
#1950000
b1110000 4
b11110 .
1"
1)
#1960000
0%
0*
0"
0)
1#
#1970000
b1110000 4
02
b1000 1
b11111 .
1"
1)
#1980000
0"
0)
#1990000
b11110000 !
b11110000 4
b0 .
1"
1)
#2000000
0"
0)
0#
#2010000
b11111110 !
b11111110 4
b1 .
1"
1)
#2020000
0"
0)
#2030000
b11111110 4
b10 .
1"
1)
#2040000
0"
0)
1#
#2050000
b11111110 4
b11 .
1"
1)
#2060000
0"
0)
#2070000
b11111110 4
b100 .
1"
1)
#2080000
0"
0)
0#
#2090000
b11111110 4
b101 .
1"
1)
#2100000
0"
0)
#2110000
b11111110 4
b110 .
1"
1)
#2120000
0"
0)
1#
#2130000
b11111110 4
b111 .
1"
1)
#2140000
0"
0)
#2150000
b11111110 4
b1000 .
1"
1)
#2160000
0"
0)
0#
#2170000
b11111110 4
b1001 .
1"
1)
#2180000
0"
0)
#2190000
b11111110 4
b1010 .
1"
1)
#2200000
0"
0)
1#
#2210000
b11111110 4
b1011 .
1"
1)
#2220000
0"
0)
#2230000
b11111110 4
b1100 .
1"
1)
#2240000
0"
0)
0#
#2250000
b11111110 4
b1101 .
1"
1)
#2260000
0"
0)
#2270000
b11111110 4
b1110 .
1"
1)
#2280000
0"
0)
1#
#2290000
b11111110 4
b1111 .
1"
1)
#2300000
0"
0)
#2310000
b11111110 4
b10000 .
1"
1)
#2320000
0"
0)
0#
#2330000
b11110000 !
b11110000 4
b10001 .
1"
1)
#2340000
0"
0)
#2350000
b11110000 4
b10010 .
1"
1)
#2360000
0"
0)
1#
#2370000
b11110000 4
b10011 .
1"
1)
#2380000
0"
0)
#2390000
b11110000 4
b10100 .
1"
1)
#2400000
0"
0)
0#
#2410000
b11110000 4
b10101 .
1"
1)
#2420000
0"
0)
#2430000
b11110000 4
b10110 .
1"
1)
#2440000
0"
0)
1#
#2450000
b11110000 4
b10111 .
1"
1)
#2460000
0"
0)
#2470000
b11110000 4
b11000 .
1"
1)
#2480000
0"
0)
0#
#2490000
b11110000 4
b11001 .
1"
1)
#2500000
0"
0)
#2510000
b11110000 4
b11010 .
1"
1)
#2520000
0"
0)
1#
#2530000
b11110000 4
b11011 .
1"
1)
#2540000
0"
0)
#2550000
b11110000 4
b11100 .
1"
1)
#2560000
0"
0)
0#
#2570000
b11110000 4
b11101 .
1"
1)
#2580000
0"
0)
#2590000
b11110000 4
b11110 .
1"
1)
#2600000
0"
0)
1#
#2610000
b11110000 4
b11111 .
1"
1)
#2620000
0"
0)
#2630000
b11110000 4
b0 .
1"
1)
#2640000
0"
0)
0#
#2650000
b11111110 !
b11111110 4
b1 .
1"
1)
#2660000
0"
0)
#2670000
b11111110 4
b10 .
1"
1)
#2680000
0"
0)
1#
#2690000
b11111110 4
b11 .
1"
1)
#2700000
0"
0)
#2710000
b11111110 4
b100 .
1"
1)
#2720000
0"
0)
0#
#2730000
b11111110 4
b101 .
1"
1)
#2740000
0"
0)
#2750000
b11111110 4
b110 .
1"
1)
#2760000
0"
0)
1#
#2770000
b11111110 4
b111 .
1"
1)
#2780000
0"
0)
#2790000
b11111110 4
b1000 .
1"
1)
#2800000
0"
0)
0#
#2810000
b11111110 4
b1001 .
1"
1)
#2820000
0"
0)
#2830000
b11111110 4
b1010 .
1"
1)
#2840000
0"
0)
1#
#2850000
b11111110 4
b1011 .
1"
1)
#2860000
0"
0)
#2870000
b11111110 4
b1100 .
1"
1)
#2880000
0"
0)
0#
#2890000
b11111110 4
b1101 .
1"
1)
#2900000
0"
0)
#2910000
b11111110 4
b1110 .
1"
1)
#2920000
0"
0)
1#
#2930000
b11111110 4
b1111 .
1"
1)
#2940000
0"
0)
#2950000
b11111110 4
b10000 .
1"
1)
#2960000
0"
0)
0#
#2970000
b11110000 !
b11110000 4
b10001 .
1"
1)
#2980000
0"
0)
#2990000
b11110000 4
b10010 .
1"
1)
#3000000
0"
0)
1#
#3010000
b11110000 4
b10011 .
1"
1)
#3020000
0"
0)
#3030000
b11110000 4
b10100 .
1"
1)
#3040000
0"
0)
0#
#3050000
b11110000 4
b10101 .
1"
1)
#3060000
0"
0)
#3070000
b11110000 4
b10110 .
1"
1)
#3080000
0"
0)
1#
#3090000
b11110000 4
b10111 .
1"
1)
#3100000
0"
0)
#3110000
b11110000 4
b11000 .
1"
1)
#3120000
0"
0)
0#
#3130000
b11110000 4
b11001 .
1"
1)
#3140000
0"
0)
#3150000
b11110000 4
b11010 .
1"
1)
#3160000
0"
0)
1#
#3170000
b11110000 4
b11011 .
1"
1)
#3180000
0"
0)
#3190000
b11110000 4
b11100 .
1"
1)
#3200000
0"
0)
0#
#3210000
b11110000 4
b11101 .
1"
1)
#3220000
0"
0)
#3230000
b11110000 4
b11110 .
1"
1)
#3240000
0"
0)
1#
#3250000
b11110000 4
b11111 .
1"
1)
#3260000
0"
0)
#3270000
b11110000 4
b0 .
1"
1)
#3280000
0"
0)
0#
#3290000
b11111110 !
b11111110 4
b1 .
1"
1)
#3300000
0"
0)
#3310000
b11111110 4
b10 .
1"
1)
#3320000
0"
0)
1#
#3330000
b11111110 4
b11 .
1"
1)
#3340000
0"
0)
#3350000
b11111110 4
b100 .
1"
1)
#3360000
0"
0)
0#
#3370000
b11111110 4
b101 .
1"
1)
#3380000
0"
0)
#3390000
b11111110 4
b110 .
1"
1)
#3400000
0"
0)
1#
#3410000
b11111110 4
b111 .
1"
1)
#3420000
0"
0)
#3430000
b11111110 4
b1000 .
1"
1)
#3440000
0"
0)
0#
#3450000
b11111110 4
b1001 .
1"
1)
#3460000
0"
0)
#3470000
b11111110 4
b1010 .
1"
1)
#3480000
0"
0)
1#
#3490000
b11111110 4
b1011 .
1"
1)
#3500000
0"
0)
#3510000
b11111110 4
b1100 .
1"
1)
#3520000
0"
0)
0#
#3530000
b11111110 4
b1101 .
1"
1)
#3540000
0"
0)
#3550000
b11111110 4
b1110 .
1"
1)
#3560000
0"
0)
1#
#3570000
b11111110 4
b1111 .
1"
1)
#3580000
0"
0)
#3590000
b11111110 4
b10000 .
1"
1)
#3600000
0"
0)
0#
#3610000
b11110000 !
b11110000 4
b10001 .
1"
1)
#3620000
0"
0)
#3630000
b11110000 4
b10010 .
1"
1)
#3640000
0"
0)
1#
#3650000
b11110000 4
b10011 .
1"
1)
#3660000
0"
0)
#3670000
b11110000 4
b10100 .
1"
1)
#3680000
0"
0)
0#
#3690000
b11110000 4
b10101 .
1"
1)
#3700000
0"
0)
#3710000
b11110000 4
b10110 .
1"
1)
#3720000
0"
0)
1#
#3730000
b11110000 4
b10111 .
1"
1)
#3740000
0"
0)
#3750000
b11110000 4
b11000 .
1"
1)
#3760000
0"
0)
0#
#3770000
b11110000 4
b11001 .
1"
1)
#3780000
0"
0)
#3790000
b11110000 4
b11010 .
1"
1)
#3800000
0"
0)
1#
#3810000
b11110000 4
b11011 .
1"
1)
#3820000
0"
0)
#3830000
b11110000 4
b11100 .
1"
1)
#3840000
0"
0)
0#
#3850000
b11110000 4
b11101 .
1"
1)
#3860000
0"
0)
#3870000
b11110000 4
b11110 .
1"
1)
#3880000
0"
0)
1#
#3890000
b11110000 4
b11111 .
1"
1)
#3900000
0"
0)
#3910000
b11110000 4
b0 .
1"
1)
#3920000
0"
0)
0#
#3930000
b11111110 !
b11111110 4
b1 .
1"
1)
#3940000
0"
0)
#3950000
b11111110 4
b10 .
1"
1)
#3960000
0"
0)
1#
#3970000
b11111110 4
b11 .
1"
1)
#3980000
0"
0)
#3990000
b11111110 4
b100 .
1"
1)
#4000000
0"
0)
0#
#4010000
b11111110 4
b101 .
1"
1)
#4020000
0"
0)
#4030000
b11111110 4
b110 .
1"
1)
#4040000
0"
0)
1#
#4050000
b11111110 4
b111 .
1"
1)
#4060000
0"
0)
#4070000
b11111110 4
b1000 .
1"
1)
#4080000
0"
0)
0#
#4090000
b11111110 4
b1001 .
1"
1)
#4100000
0"
0)
#4110000
b11111110 4
b1010 .
1"
1)
#4120000
0"
0)
1#
#4130000
b11111110 4
b1011 .
1"
1)
#4140000
0"
0)
#4150000
b11111110 4
b1100 .
1"
1)
#4160000
0"
0)
0#
#4170000
b11111110 4
b1101 .
1"
1)
#4180000
0"
0)
#4190000
b11111110 4
b1110 .
1"
1)
#4200000
0"
0)
1#
#4210000
b11111110 4
b1111 .
1"
1)
#4220000
0"
0)
#4230000
b11111110 4
b10000 .
1"
1)
#4240000
0"
0)
0#
#4250000
b11110000 !
b11110000 4
b10001 .
1"
1)
#4260000
0"
0)
#4270000
b11110000 4
b10010 .
1"
1)
#4280000
0"
0)
1#
#4290000
b11110000 4
b10011 .
1"
1)
#4300000
0"
0)
#4310000
b11110000 4
b10100 .
1"
1)
#4320000
0"
0)
0#
#4330000
b11110000 4
b10101 .
1"
1)
#4340000
0"
0)
#4350000
b11110000 4
b10110 .
1"
1)
#4360000
0"
0)
1#
#4370000
b11110000 4
b10111 .
1"
1)
#4380000
0"
0)
#4390000
b11110000 4
b11000 .
1"
1)
#4400000
0"
0)
0#
#4410000
b11110000 4
b11001 .
1"
1)
#4420000
0"
0)
#4430000
b11110000 4
b11010 .
1"
1)
#4440000
0"
0)
1#
#4450000
b11110000 4
b11011 .
1"
1)
#4460000
0"
0)
#4470000
b11110000 4
b11100 .
1"
1)
#4480000
0"
0)
0#
#4490000
b11110000 4
b11101 .
1"
1)
#4500000
0"
0)
#4510000
b11110000 4
b11110 .
1"
1)
#4520000
0"
0)
1#
#4530000
b11110000 4
b11111 .
1"
1)
#4540000
0"
0)
#4550000
b11110000 4
b0 .
1"
1)
#4560000
0"
0)
0#
#4570000
b11111110 !
b11111110 4
b1 .
1"
1)
#4580000
0"
0)
#4590000
b11111110 4
b10 .
1"
1)
#4600000
0"
0)
1#
#4610000
b11111110 4
b11 .
1"
1)
#4620000
0"
0)
#4630000
b11111110 4
b100 .
1"
1)
#4640000
0"
0)
0#
#4650000
b11111110 4
b101 .
1"
1)
#4660000
0"
0)
#4670000
b11111110 4
b110 .
1"
1)
#4680000
0"
0)
1#
#4690000
b11111110 4
b111 .
1"
1)
#4700000
0"
0)
#4710000
b11111110 4
b1000 .
1"
1)
#4720000
0"
0)
0#
#4730000
b11111110 4
b1001 .
1"
1)
#4740000
0"
0)
#4750000
b11111110 4
b1010 .
1"
1)
#4760000
0"
0)
1#
#4770000
b11111110 4
b1011 .
1"
1)
#4780000
0"
0)
#4790000
b11111110 4
b1100 .
1"
1)
#4800000
0"
0)
0#
#4810000
b11111110 4
b1101 .
1"
1)
#4820000
0"
0)
#4830000
b11111110 4
b1110 .
1"
1)
#4840000
0"
0)
1#
#4850000
b11111110 4
b1111 .
1"
1)
#4860000
0"
0)
#4870000
b11111110 4
b10000 .
1"
1)
#4880000
0"
0)
0#
#4890000
b11110000 !
b11110000 4
b10001 .
1"
1)
#4900000
0"
0)
#4910000
b11110000 4
b10010 .
1"
1)
#4920000
0"
0)
1#
#4930000
b11110000 4
b10011 .
1"
1)
#4940000
0"
0)
#4950000
b11110000 4
b10100 .
1"
1)
#4960000
0"
0)
0#
#4970000
b11110000 4
b10101 .
1"
1)
#4980000
0"
0)
#4990000
b11110000 4
b10110 .
1"
1)
#5000000
0"
0)
1#
#5010000
b11110000 4
b10111 .
1"
1)
#5020000
0"
0)
#5030000
b11110000 4
b11000 .
1"
1)
#5040000
0"
0)
0#
#5050000
b11110000 4
b11001 .
1"
1)
#5060000
0"
0)
#5070000
b11110000 4
b11010 .
1"
1)
#5080000
0"
0)
1#
#5090000
b11110000 4
b11011 .
1"
1)
#5100000
0"
0)
#5110000
b11110000 4
b11100 .
1"
1)
#5120000
0"
0)
0#
#5130000
b11110000 4
b11101 .
1"
1)
#5140000
0"
0)
#5150000
b11110000 4
b11110 .
1"
1)
#5160000
0"
0)
1#
#5170000
b11110000 4
b11111 .
1"
1)
#5180000
0"
0)
#5190000
b11110000 4
b0 .
1"
1)
#5200000
0"
0)
0#
#5210000
b11111110 !
b11111110 4
b1 .
1"
1)
#5220000
0"
0)
#5230000
b11111110 4
b10 .
1"
1)
#5240000
0"
0)
1#
#5250000
b11111110 4
b11 .
1"
1)
#5260000
0"
0)
#5270000
b11111110 4
b100 .
1"
1)
#5280000
0"
0)
0#
#5290000
b11111110 4
b101 .
1"
1)
#5300000
0"
0)
#5310000
b11111110 4
b110 .
1"
1)
#5320000
0"
0)
1#
#5330000
b11111110 4
b111 .
1"
1)
#5340000
0"
0)
#5350000
b11111110 4
b1000 .
1"
1)
#5360000
0"
0)
0#
#5370000
b11111110 4
b1001 .
1"
1)
#5380000
0"
0)
#5390000
b11111110 4
b1010 .
1"
1)
#5400000
0"
0)
1#
#5410000
b11111110 4
b1011 .
1"
1)
#5420000
0"
0)
#5430000
b11111110 4
b1100 .
1"
1)
#5440000
0"
0)
0#
#5450000
b11111110 4
b1101 .
1"
1)
#5460000
0"
0)
#5470000
b11111110 4
b1110 .
1"
1)
#5480000
0"
0)
1#
#5490000
b11111110 4
b1111 .
1"
1)
#5500000
0"
0)
#5510000
b11111110 4
b10000 .
1"
1)
#5520000
0"
0)
0#
#5530000
b11110000 !
b11110000 4
b10001 .
1"
1)
#5540000
0"
0)
#5550000
b11110000 4
b10010 .
1"
1)
#5560000
0"
0)
1#
#5570000
b11110000 4
b10011 .
1"
1)
#5580000
0"
0)
#5590000
b11110000 4
b10100 .
1"
1)
#5600000
0"
0)
0#
#5610000
b11110000 4
b10101 .
1"
1)
#5620000
0"
0)
#5630000
b11110000 4
b10110 .
1"
1)
#5640000
0"
0)
1#
#5650000
b11110000 4
b10111 .
1"
1)
#5660000
0"
0)
#5670000
b11110000 4
b11000 .
1"
1)
#5680000
0"
0)
0#
#5690000
b11110000 4
b11001 .
1"
1)
#5700000
0"
0)
#5710000
b11110000 4
b11010 .
1"
1)
#5720000
0"
0)
1#
#5730000
b11110000 4
b11011 .
1"
1)
#5740000
0"
0)
#5750000
b11110000 4
b11100 .
1"
1)
#5760000
0"
0)
0#
#5770000
b11110000 4
b11101 .
1"
1)
#5780000
0"
0)
#5790000
b11110000 4
b11110 .
1"
1)
#5800000
0"
0)
1#
#5810000
b11110000 4
b11111 .
1"
1)
#5820000
0"
0)
#5830000
b11110000 4
b0 .
1"
1)
#5840000
0"
0)
0#
#5850000
b11111110 !
b11111110 4
b1 .
1"
1)
#5860000
0"
0)
#5870000
b11111110 4
b10 .
1"
1)
#5880000
0"
0)
1#
#5890000
b11111110 4
b11 .
1"
1)
#5900000
0"
0)
#5910000
b11111110 4
b100 .
1"
1)
#5920000
0"
0)
0#
#5930000
b11111110 4
b101 .
1"
1)
#5940000
0"
0)
#5950000
b11111110 4
b110 .
1"
1)
#5960000
0"
0)
1#
#5970000
b11111110 4
b111 .
1"
1)
#5980000
0"
0)
#5990000
b11111110 4
b1000 .
1"
1)
#6000000
0"
0)
0#
#6010000
b11111110 4
b1001 .
1"
1)
#6020000
0"
0)
#6030000
b11111110 4
b1010 .
1"
1)
#6040000
0"
0)
1#
#6050000
b11111110 4
b1011 .
1"
1)
#6060000
0"
0)
#6070000
b11111110 4
b1100 .
1"
1)
#6080000
0"
0)
0#
#6090000
b11111110 4
b1101 .
1"
1)
#6100000
0"
0)
#6110000
b11111110 4
b1110 .
1"
1)
#6120000
0"
0)
1#
#6130000
b11111110 4
b1111 .
1"
1)
#6140000
0"
0)
#6150000
b11111110 4
b10000 .
1"
1)
#6160000
0"
0)
0#
#6170000
b11110000 !
b11110000 4
b10001 .
1"
1)
#6180000
0"
0)
#6190000
b11110000 4
b10010 .
1"
1)
#6200000
0"
0)
1#
#6210000
b11110000 4
b10011 .
1"
1)
#6220000
0"
0)
#6230000
b11110000 4
b10100 .
1"
1)
#6240000
0"
0)
0#
#6250000
b11110000 4
b10101 .
1"
1)
#6260000
0"
0)
#6270000
b11110000 4
b10110 .
1"
1)
#6280000
0"
0)
1#
#6290000
b11110000 4
b10111 .
1"
1)
#6300000
0"
0)
#6310000
b11110000 4
b11000 .
1"
1)
#6320000
0"
0)
0#
#6330000
b11110000 4
b11001 .
1"
1)
#6340000
0"
0)
#6350000
b11110000 4
b11010 .
1"
1)
#6360000
0"
0)
1#
#6370000
b11110000 4
b11011 .
1"
1)
#6380000
0"
0)
#6390000
b11110000 4
b11100 .
1"
1)
#6400000
0"
0)
0#
#6410000
b11110000 4
b11101 .
1"
1)
#6420000
0"
0)
#6430000
b11110000 4
b11110 .
1"
1)
#6440000
0"
0)
1#
#6450000
b11110000 4
b11111 .
1"
1)
#6460000
0"
0)
#6470000
b11110000 4
b0 .
1"
1)
#6480000
0"
0)
0#
#6490000
b11111110 !
b11111110 4
b1 .
1"
1)
#6500000
0"
0)
#6510000
b11111110 4
b10 .
1"
1)
#6520000
0"
0)
1#
#6530000
b11111110 4
b11 .
1"
1)
#6540000
0"
0)
#6550000
b11111110 4
b100 .
1"
1)
#6560000
0"
0)
0#
